kelley_portfolio_optimization.py
kelley_portfolio_optimization-0.0.2.dist-info/LICENSE.txt
kelley_portfolio_optimization-0.0.2.dist-info/METADATA
kelley_portfolio_optimization-0.0.2.dist-info/WHEEL
kelley_portfolio_optimization-0.0.2.dist-info/top_level.txt
kelley_portfolio_optimization-0.0.2.dist-info/RECORD
