Metadata-Version: 2.1
Name: kelley-portfolio-optimization
Version: 0.0.2
Summary: Portfolio Optimization
Home-page: https://github.com/chrisebell24/kelley_portfolio_optimization
Author: Christopher Bell
Author-email: Chris.E.Bell24@gmail.com
Maintainer: Christopher Bell
Maintainer-email: Chris.E.Bell24@gmail.com
License: UNKNOWN
Platform: UNKNOWN
Classifier: Programming Language :: Python :: 3
Classifier: Programming Language :: Python :: 3.6
Classifier: Programming Language :: Python :: 3.7
Classifier: License :: OSI Approved :: GNU General Public License v2 or later (GPLv2+)
Classifier: Operating System :: OS Independent
Requires-Dist: numpy (>=1.16.1)
Requires-Dist: pandas (>=1.0.0)
Requires-Dist: wget (>=3.2)
Requires-Dist: pyomo (>=6.3.0)
Provides-Extra: dev
Requires-Dist: pytest (>=3.7) ; extra == 'dev'
